odoo/addons/partner_bank_acc_holder_name/README.rst
odoo/addons/partner_bank_acc_holder_name/__init__.py
odoo/addons/partner_bank_acc_holder_name/__manifest__.py
odoo/addons/partner_bank_acc_holder_name/i18n/partner_bank_acc_holder_name.pot
odoo/addons/partner_bank_acc_holder_name/readme/CONTRIBUTORS.md
odoo/addons/partner_bank_acc_holder_name/readme/DESCRIPTION.md
odoo/addons/partner_bank_acc_holder_name/static/description/icon.png
odoo/addons/partner_bank_acc_holder_name/static/description/index.html
odoo/addons/partner_bank_acc_holder_name/views/res_partner_bank_views.xml
odoo_addon_partner_bank_acc_holder_name-18.0.1.0.0.2.dist-info/METADATA
odoo_addon_partner_bank_acc_holder_name-18.0.1.0.0.2.dist-info/WHEEL
odoo_addon_partner_bank_acc_holder_name-18.0.1.0.0.2.dist-info/top_level.txt
odoo_addon_partner_bank_acc_holder_name-18.0.1.0.0.2.dist-info/RECORD
